pyside_setup_macro/__init__.py
pyside_setup_macro/__main__.py
pyside_setup_macro/_qmacro.py
pyside_setup_macro/_qt.py
pyside_setup_macro-0.1.1.dist-info/LICENSE
pyside_setup_macro-0.1.1.dist-info/METADATA
pyside_setup_macro-0.1.1.dist-info/WHEEL
pyside_setup_macro-0.1.1.dist-info/top_level.txt
pyside_setup_macro-0.1.1.dist-info/RECORD
